{
  "name": "SolidStart",
  "package": "starter-solid-start",
  "isFocused": true,
  "type": "starter-kit",
  "prodDependencies": 5,
  "devDependencies": 0,
  "timingMeasuredAt": "2026-02-22T21:54:40.454Z",
  "runner": "ubuntu-latest",
  "installTimeMs": 3935,
  "nodeModulesSize": 168345600,
  "nodeModulesSizeProdOnly": 168345600,
  "coldBuildTimeMs": 9919,
  "warmBuildTimeMs": 9551,
  "buildOutputSize": 888832,
  "frameworkVersion": "1.2.1",
  "avgInstallTimeMs": 3066.2,
  "minInstallTimeMs": 2586,
  "maxInstallTimeMs": 4638,
  "coldBuildTime": {
    "avgMs": 8395.6,
    "minMs": 8246,
    "maxMs": 8917
  },
  "warmBuildTime": {
    "avgMs": 8296,
    "minMs": 8183,
    "maxMs": 8589
  },
  "installTime": {
    "avgMs": 2523.4,
    "minMs": 2382,
    "maxMs": 2881
  },
  "order": 6
}
